napari_layer_details_display/__init__.py
napari_layer_details_display/_dock_widget.py
napari_layer_details_display/_tests/__init__.py
napari_layer_details_display/_tests/test_dock_widget.py
napari_layer_details_display-0.1.5.dist-info/LICENSE
napari_layer_details_display-0.1.5.dist-info/METADATA
napari_layer_details_display-0.1.5.dist-info/WHEEL
napari_layer_details_display-0.1.5.dist-info/entry_points.txt
napari_layer_details_display-0.1.5.dist-info/top_level.txt
napari_layer_details_display-0.1.5.dist-info/RECORD
